chunkifypy/__init__.py
chunkifypy/chunkify.py
chunkifypy-0.0.1.dist-info/LICENSE
chunkifypy-0.0.1.dist-info/METADATA
chunkifypy-0.0.1.dist-info/WHEEL
chunkifypy-0.0.1.dist-info/RECORD
