Metadata-Version: 2.1
Name: chunkifypy
Version: 0.0.1
Summary: ChunkifyPy is a Python package designed to simplify the process of breaking down sizable Python objects into smaller, manageable chunks. This package is an invaluable tool for applications requiring seamless streaming or transmission of data in controlled portions.
Author: Kaustubh Shirpurkar
Author-email: kaustubh.shirpurkar@gmail.com
Requires-Python: >=3.10,<4.0
Classifier: License :: OSI Approved :: MIT License
Classifier: Operating System :: OS Independent
Classifier: Programming Language :: Python :: 3
Classifier: Programming Language :: Python :: 3.10
Classifier: Programming Language :: Python :: 3.11
Requires-Dist: more-itertools (>=10.1.0,<11.0.0)
Project-URL: repository, https://github.com/Kk-ships/chunkifypy
